Metadata-Version: 1.0
Name: jum-probabillity
Version: 1.0
Summary: Gaussian and Binomial distributions
Home-page: UNKNOWN
Author: Jesper Schumacher
Author-email: mail4jms@gmail.com
License: UNKNOWN
Platform: UNKNOWN
